xcolumns/__init__.py
xcolumns/block_coordinate.py
xcolumns/default_types.py
xcolumns/find_classifier_frank_wolfe.py
xcolumns/metrics.py
xcolumns/numba_csr_methods.py
xcolumns/online_block_coordinate.py
xcolumns/utils.py
xcolumns/weighted_prediction.py
xcolumns-0.0.1.dist-info/LICENSE
xcolumns-0.0.1.dist-info/METADATA
xcolumns-0.0.1.dist-info/WHEEL
xcolumns-0.0.1.dist-info/top_level.txt
xcolumns-0.0.1.dist-info/RECORD
