Metadata-Version: 2.1
Name: xcolumns
Version: 0.0.1
Summary: A small library for Consistent Optimization of Label-wise Utilities in Multi-label clasifficatioN
Author-email: "Marek Wydmuch, Erik Schultheis, Wojciech Kotłowski, Rohit Babbar, Krzysztof Dembczyński" <mwydmuch@cs.put.poznan.pl>
License: MIT License
Project-URL: Homepage, https://github.com/mwydmuch/xcolumns
Project-URL: Repository, https://github.com/mwydmuch/xcolumns
Project-URL: Documentation, https://github.com/mwydmuch/xcolumns
Project-URL: Bug Report, https://github.com/mwydmuch/xcolumns/issues
Keywords: machine learning,multi-label classification,performance metrics,label-wise utilities,classification metrics,macro-measures,optimization
Classifier: Development Status :: 4 - Beta
Classifier: License :: OSI Approved :: MIT License
Classifier: Programming Language :: Python :: 3
Classifier: Programming Language :: Python :: 3.8
Classifier: Programming Language :: Python :: 3.9
Classifier: Programming Language :: Python :: 3.10
Classifier: Programming Language :: Python :: 3.11
Classifier: Programming Language :: Python :: 3.12
Classifier: Intended Audience :: Developers
Classifier: Intended Audience :: Science/Research
Classifier: Topic :: Scientific/Engineering :: Artificial Intelligence
Requires-Python: >=3.8
License-File: LICENSE
Requires-Dist: numpy
Requires-Dist: scipy
Requires-Dist: numba >=0.58.0
Requires-Dist: click
Requires-Dist: torch
Requires-Dist: tqdm
